gamejolt.py
gamejolt-1.dist-info/LICENSE
gamejolt-1.dist-info/METADATA
gamejolt-1.dist-info/WHEEL
gamejolt-1.dist-info/top_level.txt
gamejolt-1.dist-info/RECORD
